{"index":{"_id":0}}
{"user_number":0,"grade":71,"name":"Lillie O'Hara","weight":74}
{"index":{"_id":1}}
{"user_number":1,"grade":75,"name":"Ari Gutkowski","weight":76}
{"index":{"_id":2}}
{"user_number":2,"grade":85,"name":"Arnulfo Lang","weight":64}
{"index":{"_id":3}}
{"user_number":3,"grade":50,"name":"Royal Goldner","weight":58}
{"index":{"_id":4}}
{"user_number":4,"grade":68,"name":"Nash Emmerich III","weight":27}
{"index":{"_id":5}}
{"user_number":5,"grade":95,"name":"Miss Casandra Denesik","weight":94}
{"index":{"_id":6}}
{"user_number":6,"grade":99,"name":"Mrs. Dayana Stanton","weight":15}
{"index":{"_id":7}}
{"user_number":7,"grade":79,"name":"Mr. Cali Schumm","weight":91}
{"index":{"_id":8}}
{"user_number":8,"grade":23,"name":"Dena Kuhn I","weight":45}
{"index":{"_id":9}}
{"user_number":9,"grade":26,"name":"Jacky Hauck","weight":46}
{"index":{"_id":0}}
{"user_number":0,"grade":32,"name":"Gabe Kilback","weight":25}
{"index":{"_id":1}}
{"user_number":1,"grade":19,"name":"Catherine O'Hara","weight":36}
{"index":{"_id":2}}
{"user_number":2,"grade":69,"name":"Ramiro Cummerata","weight":53}
{"index":{"_id":3}}
{"user_number":3,"grade":92,"name":"Nella Crooks","weight":89}
{"index":{"_id":4}}
{"user_number":4,"grade":34,"name":"Levi Kutch","weight":74}
{"index":{"_id":5}}
{"user_number":5,"grade":46,"name":"Melba Bahringer","weight":73}
{"index":{"_id":6}}
{"user_number":6,"grade":9,"name":"Cecelia Donnelly","weight":70}
{"index":{"_id":7}}
{"user_number":7,"grade":71,"name":"Kayli Tremblay","weight":49}
{"index":{"_id":8}}
{"user_number":8,"grade":20,"name":"Timmothy Dare","weight":85}
{"index":{"_id":9}}
{"user_number":9,"grade":70,"name":"Vicente Becker V","weight":41}
{"index":{"_id":0}}
{"user_number":0,"grade":70,"name":"king","weight":56}
{"index":{"_id":1}}
{"user_number":1,"grade":73,"name":"kali","weight":21}
{"index":{"_id":2}}
{"user_number":2,"grade":31,"name":"linux","weight":86}
{"index":{"_id":0}}
{"user_number":0,"grade":55,"name":"Frieda Stiedemann","weight":3}
{"index":{"_id":1}}
{"user_number":1,"grade":4,"name":"Raphael Haag","weight":88}
{"index":{"_id":2}}
{"user_number":2,"grade":67,"name":"Allen Mante","weight":81}
{"index":{"_id":3}}
{"user_number":3,"grade":53,"name":"Tierra Hammes","weight":4}
{"index":{"_id":4}}
{"user_number":4,"grade":55,"name":"Vivian Towne","weight":22}
{"index":{"_id":5}}
{"user_number":5,"grade":21,"name":"Nathan Dietrich","weight":39}
{"index":{"_id":6}}
{"user_number":6,"grade":99,"name":"Dr. Hank Will","weight":92}
{"index":{"_id":7}}
{"user_number":7,"grade":43,"name":"Aliza Frami DDS","weight":90}
{"index":{"_id":8}}
{"user_number":8,"grade":61,"name":"Rodrigo Dibbert","weight":37}
{"index":{"_id":9}}
{"user_number":9,"grade":94,"name":"Una Gislason","weight":29}
{"index":{"_id":0}}
{"user_number":0,"grade":31,"name":"Marlene Abshire","weight":50}
{"index":{"_id":1}}
{"user_number":1,"grade":47,"name":"Madge Mosciski","weight":8}
{"index":{"_id":2}}
{"user_number":2,"grade":80,"name":"May King","weight":3}
{"index":{"_id":3}}
{"user_number":3,"grade":15,"name":"Tianna Hyatt","weight":38}
{"index":{"_id":4}}
{"user_number":4,"grade":71,"name":"Deja Morissette","weight":61}
{"index":{"_id":5}}
{"user_number":5,"grade":95,"name":"Laisha Goyette Sr.","weight":58}
{"index":{"_id":6}}
{"user_number":6,"grade":37,"name":"Thelma Lemke","weight":49}
{"index":{"_id":7}}
{"user_number":7,"grade":16,"name":"Garnet Mohr","weight":61}
{"index":{"_id":8}}
{"user_number":8,"grade":56,"name":"Rubie Labadie","weight":0}
{"index":{"_id":9}}
{"user_number":9,"grade":7,"name":"Laury Ortiz","weight":30}
{"index":{"_id":0}}
{"user_number":0,"grade":38,"name":"Ray Muller","weight":62}
{"index":{"_id":1}}
{"user_number":1,"grade":75,"name":"Ms. Rocky Raynor","weight":17}
{"index":{"_id":2}}
{"user_number":2,"grade":82,"name":"Jesse Crooks","weight":93}
{"index":{"_id":3}}
{"user_number":3,"grade":93,"name":"Joey Spinka","weight":91}
{"index":{"_id":4}}
{"user_number":4,"grade":98,"name":"Gertrude Hills","weight":62}
{"index":{"_id":5}}
{"user_number":5,"grade":9,"name":"Idell Konopelski MD","weight":50}
{"index":{"_id":6}}
{"user_number":6,"grade":12,"name":"Mrs. Heath Kutch","weight":85}
{"index":{"_id":7}}
{"user_number":7,"grade":28,"name":"Rusty Gutkowski","weight":47}
{"index":{"_id":8}}
{"user_number":8,"grade":27,"name":"Ethyl Streich","weight":88}
{"index":{"_id":9}}
{"user_number":9,"grade":0,"name":"Mrs. Sonny McGlynn","weight":27}
{"index":{"_id":0}}
{"user_number":0,"grade":21,"name":"Stefan Collier","weight":44}
{"index":{"_id":1}}
{"user_number":1,"grade":78,"name":"Ottis Anderson","weight":43}
{"index":{"_id":2}}
{"user_number":2,"grade":7,"name":"Sophia Heathcote","weight":45}
{"index":{"_id":3}}
{"user_number":3,"grade":44,"name":"Johnathan Kub","weight":26}
{"index":{"_id":4}}
{"user_number":4,"grade":20,"name":"Dr. Dayton Conroy","weight":74}
{"index":{"_id":5}}
{"user_number":5,"grade":43,"name":"Norbert Batz","weight":26}
{"index":{"_id":6}}
{"user_number":6,"grade":73,"name":"Dr. Destini Wunsch","weight":85}
{"index":{"_id":7}}
{"user_number":7,"grade":15,"name":"Rubie Harris","weight":15}
{"index":{"_id":8}}
{"user_number":8,"grade":26,"name":"Ms. Summer Hessel","weight":95}
{"index":{"_id":9}}
{"user_number":9,"grade":39,"name":"Erling Murazik","weight":89}
{"index":{"_id":0}}
{"user_number":0,"grade":18,"name":"Andy Russel","weight":32}
{"index":{"_id":1}}
{"user_number":1,"grade":14,"name":"Casimer Gerlach","weight":43}
{"index":{"_id":2}}
{"user_number":2,"grade":33,"name":"Destini D'Amore III","weight":77}
{"index":{"_id":3}}
{"user_number":3,"grade":49,"name":"Mrs. Ayana Lowe","weight":62}
{"index":{"_id":4}}
{"user_number":4,"grade":41,"name":"Ezra Cummerata","weight":0}
{"index":{"_id":5}}
{"user_number":5,"grade":66,"name":"Austin Robel","weight":16}
{"index":{"_id":6}}
{"user_number":6,"grade":49,"name":"Arturo Krajcik","weight":19}
{"index":{"_id":7}}
{"user_number":7,"grade":69,"name":"Miss Brando Stanton","weight":19}
{"index":{"_id":8}}
{"user_number":8,"grade":49,"name":"Nelson Lubowitz","weight":24}
{"index":{"_id":9}}
{"user_number":9,"grade":72,"name":"Nyasia Weimann","weight":76}
{"index":{"_id":0}}
{"user_number":0,"grade":49,"name":"Ruthie Towne","weight":38}
{"index":{"_id":1}}
{"user_number":1,"grade":85,"name":"Jaden Farrell","weight":3}
{"index":{"_id":2}}
{"user_number":2,"grade":72,"name":"Mrs. Aylin Klocko","weight":23}
{"index":{"_id":3}}
{"user_number":3,"grade":91,"name":"Kareem Cassin","weight":26}
{"index":{"_id":4}}
{"user_number":4,"grade":12,"name":"Izaiah Emmerich","weight":37}
{"index":{"_id":5}}
{"user_number":5,"grade":94,"name":"Mustafa Kuphal","weight":30}
{"index":{"_id":6}}
{"user_number":6,"grade":88,"name":"Shana Jerde","weight":19}
{"index":{"_id":7}}
{"user_number":7,"grade":97,"name":"Dayne Considine DDS","weight":2}
{"index":{"_id":8}}
{"user_number":8,"grade":59,"name":"Yolanda Padberg","weight":15}
{"index":{"_id":9}}
{"user_number":9,"grade":46,"name":"Judy Luettgen","weight":26}
{"index":{"_id":0}}
{"user_number":0,"grade":34,"name":"Katelyn Collins","weight":89}
{"index":{"_id":1}}
{"user_number":1,"grade":79,"name":"Olga Lesch","weight":37}
{"index":{"_id":2}}
{"user_number":2,"grade":39,"name":"Darlene Ullrich","weight":53}
{"index":{"_id":3}}
{"user_number":3,"grade":7,"name":"Piper Johnson","weight":98}
{"index":{"_id":4}}
{"user_number":4,"grade":29,"name":"Leif O'Reilly","weight":2}
{"index":{"_id":5}}
{"user_number":5,"grade":72,"name":"Bennett Stoltenberg","weight":24}
{"index":{"_id":6}}
{"user_number":6,"grade":40,"name":"Shawna Murphy","weight":90}
{"index":{"_id":7}}
{"user_number":7,"grade":86,"name":"Ally McLaughlin","weight":37}
{"index":{"_id":8}}
{"user_number":8,"grade":12,"name":"Davion Sanford","weight":25}
{"index":{"_id":9}}
{"user_number":9,"grade":3,"name":"Ms. Raquel Kunde","weight":81}
{"index":{"_id":0}}
{"user_number":0,"grade":14,"name":"Kade Considine","weight":34}
{"index":{"_id":1}}
{"user_number":1,"grade":6,"name":"Andy Thiel","weight":17}
{"index":{"_id":2}}
{"user_number":2,"grade":11,"name":"Steve Feest","weight":51}
{"index":{"_id":3}}
{"user_number":3,"grade":39,"name":"Darius Hessel","weight":82}
{"index":{"_id":4}}
{"user_number":4,"grade":51,"name":"Eveline Davis","weight":13}
{"index":{"_id":5}}
{"user_number":5,"grade":91,"name":"Marshall Powlowski","weight":95}
{"index":{"_id":6}}
{"user_number":6,"grade":88,"name":"Dina Block","weight":24}
{"index":{"_id":7}}
{"user_number":7,"grade":16,"name":"Norberto Moore","weight":84}
{"index":{"_id":8}}
{"user_number":8,"grade":57,"name":"Constantin Jewess","weight":85}
{"index":{"_id":9}}
{"user_number":9,"grade":2,"name":"Miss Rae Graham","weight":85}
{"index":{"_id":0}}
{"user_number":0,"grade":83,"name":"Sigrid Krajcik","weight":47}
{"index":{"_id":1}}
{"user_number":1,"grade":70,"name":"Priscilla White","weight":84}
{"index":{"_id":2}}
{"user_number":2,"grade":63,"name":"Eva Predovic","weight":46}
{"index":{"_id":3}}
{"user_number":3,"grade":81,"name":"Lesley Morar","weight":38}
{"index":{"_id":4}}
{"user_number":4,"grade":78,"name":"Jaunita Wintheiser","weight":37}
{"index":{"_id":5}}
{"user_number":5,"grade":80,"name":"Miss King Stoltenberg","weight":4}
{"index":{"_id":6}}
{"user_number":6,"grade":64,"name":"Jarrell Bogisich III","weight":18}
{"index":{"_id":7}}
{"user_number":7,"grade":37,"name":"Piper Stark","weight":57}
{"index":{"_id":8}}
{"user_number":8,"grade":97,"name":"Carlo Bahringer","weight":18}
{"index":{"_id":9}}
{"user_number":9,"grade":24,"name":"Jaime Bernhard","weight":35}
{"index":{"_id":0}}
{"user_number":0,"grade":90,"name":"Vito Bernhard","weight":62}
{"index":{"_id":1}}
{"user_number":1,"grade":0,"name":"Isadore Herzog","weight":64}
{"index":{"_id":2}}
{"user_number":2,"grade":70,"name":"Andres Lakin","weight":36}
{"index":{"_id":3}}
{"user_number":3,"grade":4,"name":"Filiberto Luettgen","weight":28}
{"index":{"_id":4}}
{"user_number":4,"grade":45,"name":"Miss Jerry Roberts","weight":79}
{"index":{"_id":5}}
{"user_number":5,"grade":60,"name":"Miss Aglae Von","weight":9}
{"index":{"_id":6}}
{"user_number":6,"grade":37,"name":"Eldred Kunde PhD","weight":7}
{"index":{"_id":7}}
{"user_number":7,"grade":79,"name":"Rowland Keebler","weight":66}
{"index":{"_id":8}}
{"user_number":8,"grade":30,"name":"Karianne Cormier PhD","weight":44}
{"index":{"_id":9}}
{"user_number":9,"grade":61,"name":"Francis Schumm","weight":12}
{"index":{"_id":0}}
{"user_number":0,"grade":67,"name":"Herminia Lubowitz V","weight":79}
{"index":{"_id":1}}
{"user_number":1,"grade":77,"name":"Tiara Barrows","weight":2}
{"index":{"_id":2}}
{"user_number":2,"grade":76,"name":"Sadie Gusikowski","weight":28}
{"index":{"_id":3}}
{"user_number":3,"grade":19,"name":"Litzy Senger","weight":25}
{"index":{"_id":4}}
{"user_number":4,"grade":27,"name":"Malika Runte","weight":10}
{"index":{"_id":5}}
{"user_number":5,"grade":85,"name":"Veronica Grimes","weight":18}
{"index":{"_id":6}}
{"user_number":6,"grade":91,"name":"Marta Rogahn","weight":4}
{"index":{"_id":7}}
{"user_number":7,"grade":44,"name":"Lonny Zieme","weight":72}
{"index":{"_id":8}}
{"user_number":8,"grade":77,"name":"Laverna Dibbert DVM","weight":5}
{"index":{"_id":9}}
{"user_number":9,"grade":20,"name":"Judah Weimann","weight":11}
{"index":{"_id":0}}
{"user_number":0,"grade":73,"name":"Zoie Wunsch","weight":44}
{"index":{"_id":1}}
{"user_number":1,"grade":14,"name":"Bennett Zemlak","weight":18}
{"index":{"_id":2}}
{"user_number":2,"grade":40,"name":"Albin Koelpin","weight":44}
{"index":{"_id":3}}
{"user_number":3,"grade":76,"name":"Javonte Hahn","weight":24}
{"index":{"_id":4}}
{"user_number":4,"grade":94,"name":"Ismael Roberts","weight":57}
{"index":{"_id":5}}
{"user_number":5,"grade":73,"name":"Joelle Wilkinson","weight":69}
{"index":{"_id":6}}
{"user_number":6,"grade":80,"name":"Jed VonRueden","weight":94}
{"index":{"_id":7}}
{"user_number":7,"grade":3,"name":"Courtney Dickinson","weight":55}
{"index":{"_id":8}}
{"user_number":8,"grade":77,"name":"Lorna Kulas","weight":65}
{"index":{"_id":9}}
{"user_number":9,"grade":35,"name":"Margot O'Keefe","weight":21}
{"index":{"_id":10}}
{"user_number":10,"grade":42,"name":"Kianna Marvin","weight":42}
{"index":{"_id":11}}
{"user_number":11,"grade":29,"name":"Mr. Ruthe Bosco","weight":10}
{"index":{"_id":12}}
{"user_number":12,"grade":12,"name":"Alessandra Langworth","weight":86}
{"index":{"_id":13}}
{"user_number":13,"grade":87,"name":"Birdie Green","weight":45}
{"index":{"_id":14}}
{"user_number":14,"grade":35,"name":"Heather Frami","weight":15}
{"index":{"_id":15}}
{"user_number":15,"grade":98,"name":"Ellen Ebert MD","weight":87}
{"index":{"_id":16}}
{"user_number":16,"grade":7,"name":"Lonny Torphy","weight":81}
{"index":{"_id":17}}
{"user_number":17,"grade":91,"name":"Jefferey Pollich","weight":41}
{"index":{"_id":18}}
{"user_number":18,"grade":22,"name":"Mrs. Lennie Daniel","weight":83}
{"index":{"_id":19}}
{"user_number":19,"grade":69,"name":"Leora Gutkowski","weight":75}
{"index":{"_id":20}}
{"user_number":20,"grade":63,"name":"Alden Anderson","weight":96}
{"index":{"_id":21}}
{"user_number":21,"grade":5,"name":"Adrian Littel","weight":46}
{"index":{"_id":22}}
{"user_number":22,"grade":47,"name":"Peter Barrows PhD","weight":39}
{"index":{"_id":23}}
{"user_number":23,"grade":66,"name":"Gilberto Schaden","weight":7}
{"index":{"_id":24}}
{"user_number":24,"grade":90,"name":"Mr. Jay Collier","weight":18}
{"index":{"_id":25}}
{"user_number":25,"grade":30,"name":"Theresa Leffler Sr.","weight":16}
{"index":{"_id":26}}
{"user_number":26,"grade":78,"name":"Kattie Satterfield","weight":79}
{"index":{"_id":27}}
{"user_number":27,"grade":56,"name":"Astrid Powlowski","weight":4}
{"index":{"_id":28}}
{"user_number":28,"grade":58,"name":"Maybelle Green","weight":99}
{"index":{"_id":29}}
{"user_number":29,"grade":8,"name":"Bernardo Volkman","weight":69}
{"index":{"_id":30}}
{"user_number":30,"grade":69,"name":"Hank Schoen","weight":62}
{"index":{"_id":31}}
{"user_number":31,"grade":79,"name":"Jazmin Murphy I","weight":83}
{"index":{"_id":32}}
{"user_number":32,"grade":55,"name":"Miss Zelma Reynolds","weight":25}
{"index":{"_id":33}}
{"user_number":33,"grade":47,"name":"Daniella Welch","weight":25}
{"index":{"_id":34}}
{"user_number":34,"grade":57,"name":"Abby Wiza","weight":78}
{"index":{"_id":35}}
{"user_number":35,"grade":45,"name":"Stuart Schmeler","weight":97}
{"index":{"_id":36}}
{"user_number":36,"grade":56,"name":"Faustino Wiegand","weight":88}
{"index":{"_id":37}}
{"user_number":37,"grade":75,"name":"Kathlyn Langworth DDS","weight":58}
{"index":{"_id":38}}
{"user_number":38,"grade":66,"name":"Johan Waelchi","weight":43}
{"index":{"_id":39}}
{"user_number":39,"grade":26,"name":"Houston Hane","weight":10}
{"index":{"_id":40}}
{"user_number":40,"grade":6,"name":"Mrs. Erna Breitenberg","weight":81}
{"index":{"_id":41}}
{"user_number":41,"grade":40,"name":"Eldora Cummings","weight":4}
{"index":{"_id":42}}
{"user_number":42,"grade":64,"name":"Cristian Miller","weight":94}
{"index":{"_id":43}}
{"user_number":43,"grade":21,"name":"Adrianna Haley","weight":47}
{"index":{"_id":44}}
{"user_number":44,"grade":38,"name":"May Dietrich","weight":53}
{"index":{"_id":45}}
{"user_number":45,"grade":45,"name":"Easton Daniel DVM","weight":29}
{"index":{"_id":46}}
{"user_number":46,"grade":84,"name":"Dillon Altenwerth","weight":40}
{"index":{"_id":47}}
{"user_number":47,"grade":74,"name":"Thomas Nikolaus","weight":6}
{"index":{"_id":48}}
{"user_number":48,"grade":9,"name":"Dr. Odessa Corwin","weight":52}
{"index":{"_id":49}}
{"user_number":49,"grade":53,"name":"Ruby Rice","weight":24}
{"index":{"_id":50}}
{"user_number":50,"grade":34,"name":"Madonna Batz","weight":9}
{"index":{"_id":51}}
{"user_number":51,"grade":3,"name":"Miss Maybelle Macejkovic","weight":93}
{"index":{"_id":52}}
{"user_number":52,"grade":56,"name":"Mayra Kerluke","weight":67}
{"index":{"_id":53}}
{"user_number":53,"grade":90,"name":"Skyla Wyman","weight":38}
{"index":{"_id":54}}
{"user_number":54,"grade":16,"name":"Ramona Fahey","weight":32}
{"index":{"_id":55}}
{"user_number":55,"grade":33,"name":"Narciso Rippin","weight":70}
{"index":{"_id":56}}
{"user_number":56,"grade":26,"name":"Harmon Marvin","weight":68}
{"index":{"_id":57}}
{"user_number":57,"grade":60,"name":"Miss Eusebio Weissnat","weight":86}
{"index":{"_id":58}}
{"user_number":58,"grade":12,"name":"Greg Tremblay","weight":45}
{"index":{"_id":59}}
{"user_number":59,"grade":65,"name":"Terrence Pagac","weight":11}
{"index":{"_id":60}}
{"user_number":60,"grade":72,"name":"Isaias Welch","weight":59}
{"index":{"_id":61}}
{"user_number":61,"grade":4,"name":"Talia Kihn","weight":67}
{"index":{"_id":62}}
{"user_number":62,"grade":88,"name":"Stephan Wyman","weight":61}
{"index":{"_id":63}}
{"user_number":63,"grade":39,"name":"Elenora Turcotte","weight":17}
{"index":{"_id":64}}
{"user_number":64,"grade":37,"name":"Dane Gibson","weight":36}
{"index":{"_id":65}}
{"user_number":65,"grade":73,"name":"Zackery Johnston","weight":92}
{"index":{"_id":66}}
{"user_number":66,"grade":46,"name":"Gerson Schmitt","weight":6}
{"index":{"_id":67}}
{"user_number":67,"grade":88,"name":"Krystal Hermiston","weight":55}
{"index":{"_id":68}}
{"user_number":68,"grade":26,"name":"Holly Lind","weight":87}
{"index":{"_id":69}}
{"user_number":69,"grade":58,"name":"Karson Bauch","weight":80}
{"index":{"_id":70}}
{"user_number":70,"grade":22,"name":"Nicholaus O'Conner","weight":72}
{"index":{"_id":71}}
{"user_number":71,"grade":25,"name":"Madelyn Weber","weight":61}
{"index":{"_id":72}}
{"user_number":72,"grade":45,"name":"Helmer Swift","weight":71}
{"index":{"_id":73}}
{"user_number":73,"grade":96,"name":"Ms. Queen Tremblay","weight":32}
{"index":{"_id":74}}
{"user_number":74,"grade":26,"name":"Deborah Adams","weight":76}
{"index":{"_id":75}}
{"user_number":75,"grade":32,"name":"Euna Green","weight":28}
{"index":{"_id":76}}
{"user_number":76,"grade":73,"name":"Miss Alta Kovacek","weight":33}
{"index":{"_id":77}}
{"user_number":77,"grade":49,"name":"Troy Goldner","weight":21}
{"index":{"_id":78}}
{"user_number":78,"grade":86,"name":"Sydnie Berge","weight":64}
{"index":{"_id":79}}
{"user_number":79,"grade":79,"name":"Dakota Cormier","weight":28}
{"index":{"_id":80}}
{"user_number":80,"grade":22,"name":"Shaylee Beatty","weight":2}
{"index":{"_id":81}}
{"user_number":81,"grade":25,"name":"Beryl Hahn IV","weight":24}
{"index":{"_id":82}}
{"user_number":82,"grade":25,"name":"Jonatan Olson","weight":96}
{"index":{"_id":83}}
{"user_number":83,"grade":35,"name":"Jerel Feest","weight":47}
{"index":{"_id":84}}
{"user_number":84,"grade":11,"name":"Vidal Sporer","weight":5}
{"index":{"_id":85}}
{"user_number":85,"grade":50,"name":"Rory Balistreri PhD","weight":26}
{"index":{"_id":86}}
{"user_number":86,"grade":72,"name":"Lura Hermiston","weight":17}
{"index":{"_id":87}}
{"user_number":87,"grade":10,"name":"Tianna Smith Sr.","weight":59}
{"index":{"_id":88}}
{"user_number":88,"grade":75,"name":"Omer Walker","weight":38}
{"index":{"_id":89}}
{"user_number":89,"grade":25,"name":"Waino Hartmann","weight":14}
{"index":{"_id":90}}
{"user_number":90,"grade":23,"name":"Giovanny Jaskolski","weight":34}
{"index":{"_id":91}}
{"user_number":91,"grade":8,"name":"Mrs. Hector Moen","weight":67}
{"index":{"_id":92}}
{"user_number":92,"grade":7,"name":"Jacey Legros","weight":17}
{"index":{"_id":93}}
{"user_number":93,"grade":94,"name":"Maryam Lehner","weight":36}
{"index":{"_id":94}}
{"user_number":94,"grade":4,"name":"Gregorio Russel","weight":75}
{"index":{"_id":95}}
{"user_number":95,"grade":25,"name":"Van Hirthe","weight":20}
{"index":{"_id":96}}
{"user_number":96,"grade":86,"name":"Richie Strosin","weight":92}
{"index":{"_id":97}}
{"user_number":97,"grade":88,"name":"Jaunita Quitzon","weight":10}
{"index":{"_id":98}}
{"user_number":98,"grade":31,"name":"Mr. Justice Hessel","weight":47}
{"index":{"_id":99}}
{"user_number":99,"grade":77,"name":"Alek Carter","weight":23}
